odoo/addons/edi_voxel_sale_secondary_unit/README.rst
odoo/addons/edi_voxel_sale_secondary_unit/__init__.py
odoo/addons/edi_voxel_sale_secondary_unit/__manifest__.py
odoo/addons/edi_voxel_sale_secondary_unit/i18n/edi_voxel_sale_secondary_unit.pot
odoo/addons/edi_voxel_sale_secondary_unit/models/__init__.py
odoo/addons/edi_voxel_sale_secondary_unit/models/sale_order.py
odoo/addons/edi_voxel_sale_secondary_unit/readme/CONTRIBUTORS.rst
odoo/addons/edi_voxel_sale_secondary_unit/readme/DESCRIPTION.rst
odoo/addons/edi_voxel_sale_secondary_unit/readme/USAGE.rst
odoo/addons/edi_voxel_sale_secondary_unit/static/description/icon.png
odoo/addons/edi_voxel_sale_secondary_unit/static/description/index.html
odoo/addons/edi_voxel_sale_secondary_unit/tests/__init__.py
odoo/addons/edi_voxel_sale_secondary_unit/tests/test_edi_voxel_sale_secondary_unit.py
odoo13_addon_edi_voxel_sale_secondary_unit-13.0.1.0.1.dev3.dist-info/METADATA
odoo13_addon_edi_voxel_sale_secondary_unit-13.0.1.0.1.dev3.dist-info/WHEEL
odoo13_addon_edi_voxel_sale_secondary_unit-13.0.1.0.1.dev3.dist-info/top_level.txt
odoo13_addon_edi_voxel_sale_secondary_unit-13.0.1.0.1.dev3.dist-info/RECORD
